gea/LICENSE
gea/__init__.py
gea/admin.py
gea/apps.py
gea/backup-db.sh
gea/fixtures/distritos.json.gz
gea/fixtures/zonas.json.gz
gea/forms.py
gea/gea_vars.py
gea/migrations/0001_initial.py
gea/migrations/0002_auto_20200505_1940.py
gea/migrations/0003_auto_20200506_1813.py
gea/migrations/0004_auto_20200513_1915.py
gea/migrations/0005_auto_20200520_1724.py
gea/migrations/0006_auto_20210324_1219.py
gea/migrations/0007_auto_20210324_1222.py
gea/migrations/0008_auto_20210324_1808.py
gea/migrations/__init__.py
gea/models.py
gea/static/css/bootstrap.css
gea/static/css/bootstrap.min.css
gea/static/img/folder-o.png
gea/static/img/folder.png
gea/static/img/globe.png
gea/static/img/globe_south.png
gea/static/img/mapa.png
gea/static/img/noun_16833_cc.png
gea/static/img/noun_188781_cc.png
gea/templates/about.html
gea/templates/base.html
gea/templates/gea/catastros_locales.html
gea/templates/gea/doc/solic.html
gea/templates/gea/doc/solic_form.html
gea/templates/gea/doc/visac.html
gea/templates/gea/doc/visac_form.html
gea/templates/gea/expediente_detail.html
gea/templates/gea/expediente_list.html
gea/templates/gea/persona_confirm_delete.html
gea/templates/gea/persona_detail.html
gea/templates/gea/persona_form.html
gea/templates/gea/persona_list.html
gea/templates/gea/search/catastro_form.html
gea/templates/gea/search/plano_form.html
gea/templates/gea/search/set_form.html
gea/templates/gea/tools/calendar.html
gea/templates/gea/tools/caratula.dxf
gea/templates/gea/tools/caratula.html
gea/templates/gea/tools/caratula_form.html
gea/templates/gea/tools/dvapi_form.html
gea/templates/gea/tools/sie_form.html
gea/templates/includes/_pagination.html
gea/templates/includes/topbar.html
gea/templates/index.html
gea/templates/nota.html
gea/templates/registration/logged_out.html
gea/templates/registration/login.html
gea/templatetags/__init__.py
gea/templatetags/tags.py
gea/tests.py
gea/urls.py
gea/views.py
gea-0.2.52.dist-info/LICENSE
gea-0.2.52.dist-info/WHEEL
gea-0.2.52.dist-info/METADATA
gea-0.2.52.dist-info/RECORD
