Metadata-Version: 2.1
Name: gea
Version: 0.2.52
Summary: Gestión de Expedientes de Agrimensores
Home-page: https://github.com/quijot/gea-package
License: MIT
Author: Santiago Pestarini
Author-email: santiagonob@gmail.com
Requires-Python: >=3.7,<4
Classifier: License :: OSI Approved :: MIT License
Classifier: Programming Language :: Python :: 3
Classifier: Programming Language :: Python :: 3.7
Classifier: Programming Language :: Python :: 3.8
Classifier: Programming Language :: Python :: 3.9
Requires-Dist: Django (>=3.1.7,<4.0.0)
Requires-Dist: django-crispy-forms (>=1.11.2,<2.0.0)
Requires-Dist: django-extensions (>=2.2.9,<3.0.0)
Requires-Dist: django-nested-admin (>=3.3.0,<4.0.0)
